mgp/__init__.py
mgp/imputer.py
mgp/run_experiment.py
mgp/model/__init__.py
mgp/model/callback.py
mgp/model/dataloader.py
mgp/model/dgp.py
mgp/model/kernels.py
mgp/model/layer_initializations.py
mgp/model/layers.py
mgp/model/likelihoods.py
mgp/model/mean_functions.py
mgp/model/options.py
mgp/model/train.py
mgp/model/utils.py
mgp/model/data/__init__.py
mgp/model/data/dataloader.py
mgp/model/data/preprocess.py
mgp_imputer-0.1.2.dist-info/licenses/LICENSE
mgp_imputer-0.1.2.dist-info/METADATA
mgp_imputer-0.1.2.dist-info/WHEEL
mgp_imputer-0.1.2.dist-info/top_level.txt
mgp_imputer-0.1.2.dist-info/RECORD
