Metadata-Version: 2.4
Name: mgp-imputer
Version: 0.1.2
Summary: Missing Value Imputation using Deep Gaussian Processes with a scikit-learn compatible API.
Author-email: Bahram Jafrasteh <baj4003@med.cornell.edu>
License: MIT License
Project-URL: Homepage, https://github.com/BahramJafrasteh/MissingGPs
Project-URL: Bug Tracker, https://github.com/BahramJafrasteh/MissingGPs/issues
Keywords: gaussian process,imputation,missing data,clinical data,pytorch,healthcare
Classifier: Programming Language :: Python :: 3
Classifier: License :: OSI Approved :: MIT License
Classifier: Operating System :: OS Independent
Classifier: Intended Audience :: Science/Research
Classifier: Intended Audience :: Healthcare Industry
Classifier: Topic :: Scientific/Engineering :: Bio-Informatics
Classifier: Topic :: Scientific/Engineering :: Artificial Intelligence
Classifier: Topic :: Scientific/Engineering :: Information Analysis
Classifier: Topic :: Scientific/Engineering :: Mathematics
Classifier: Topic :: Scientific/Engineering :: Medical Science Apps.
Classifier: Topic :: Software Development :: Libraries :: Python Modules
Requires-Python: >=3.8
License-File: LICENSE
Requires-Dist: numpy
Requires-Dist: scikit-learn
Requires-Dist: torch>=1.10.0
Requires-Dist: pandas
Requires-Dist: pkbar
Requires-Dist: matplotlib
Requires-Dist: scipy
Dynamic: license-file
